rss_digger/__init__.py
rss_digger/exceptions.py
rss_digger/handlers/__init__.py
rss_digger/handlers/reddit.py
rss_digger/handlers/rss.py
rss_digger/handlers/youtube.py
rss_digger-0.1.3.dist-info/LICENSE
rss_digger-0.1.3.dist-info/METADATA
rss_digger-0.1.3.dist-info/WHEEL
rss_digger-0.1.3.dist-info/top_level.txt
rss_digger-0.1.3.dist-info/RECORD
