Metadata-Version: 2.2
Name: rss-digger
Version: 0.1.3
Summary: Retrieve a RSS feed given an URL.
Requires-Python: >=3.12
License-File: LICENSE
Requires-Dist: beautifulsoup4>=4.12.3
Requires-Dist: feedparser>=6.0.11
Requires-Dist: furl>=2.1.3
Requires-Dist: httpx>=0.28.1
Requires-Dist: unidecode>=1.3.8
